rotary_states/__init__.py
rotary_states/src/__init__.py
rotary_states/src/integrators/RK4.py
rotary_states/src/integrators/__init__.py
rotary_states/src/integrators/jit_RK4.py
rotary_states/src/limit_cycles/__init__.py
rotary_states/src/limit_cycles/jit_main_method.py
rotary_states/src/limit_cycles/main_method.py
rotary_states/src/optimizers/__init__.py
rotary_states/src/optimizers/jit_newton.py
rotary_states/src/optimizers/newton.py
rotary_states/src/utils/do_jit.py
rotary_states-0.1.1.dist-info/LICENSE
rotary_states-0.1.1.dist-info/WHEEL
rotary_states-0.1.1.dist-info/METADATA
rotary_states-0.1.1.dist-info/RECORD
