Metadata-Version: 2.1
Name: rotary-states
Version: 0.1.1
Summary: The minimalistic framework for finding rotational states
Author: Dmitry Khorkin
Author-email: dmitryhorkin@gmail.com
Requires-Python: >=3.7,<3.11
Classifier: Programming Language :: Python :: 3
Classifier: Programming Language :: Python :: 3.10
Classifier: Programming Language :: Python :: 3.7
Classifier: Programming Language :: Python :: 3.8
Classifier: Programming Language :: Python :: 3.9
Requires-Dist: numba (>=0.55.0,<0.56.0)
Requires-Dist: numpy (>=1.18,<1.22)
Requires-Dist: scipy (>=1.7.3,<2.0.0)
